inklayers/__init__.py
inklayers/inklayers.py
inklayers/version.py
inklayers-0.1.1.dist-info/AUTHORS
inklayers-0.1.1.dist-info/LICENSE
inklayers-0.1.1.dist-info/METADATA
inklayers-0.1.1.dist-info/WHEEL
inklayers-0.1.1.dist-info/entry_points.txt
inklayers-0.1.1.dist-info/top_level.txt
inklayers-0.1.1.dist-info/RECORD
