Metadata-Version: 2.1
Name: inklayers
Version: 0.1.1
Summary: Export SVG layers to create slideshows and presentations
Home-page: https://github.com/toolleeo/inklayers
Author: Tullio Facchinetti
Author-email: toolleeo@gmail.com
License: GPL-3
Classifier: Programming Language :: Python :: 3
Classifier: Operating System :: OS Independent
License-File: LICENSE
License-File: AUTHORS
Requires-Dist: configparser
Requires-Dist: inkex
Requires-Dist: lxml
Requires-Dist: pytoml
Requires-Dist: semantic-version
